setup.py
Flask_ErrorMail.egg-info/PKG-INFO
Flask_ErrorMail.egg-info/SOURCES.txt
Flask_ErrorMail.egg-info/dependency_links.txt
Flask_ErrorMail.egg-info/not-zip-safe
Flask_ErrorMail.egg-info/requires.txt
Flask_ErrorMail.egg-info/top_level.txt
flask_errormail/__init__.py