Metadata-Version: 1.0
Name: Flask-ErrorMail
Version: 0.2.0
Summary: Flask extension for sending administrators e-mails with stacktraces when internal server errors occur.
Home-page: http://github.com/jasonwyatt/Flask-ErrorMail
Author: Jason Wyatt Feinstein
Author-email: jason.feinstein@gmail.com
License: MIT
Platform: any
Classifier: Development Status :: 2 - Pre-Alpha
Classifier: Environment :: Web Environment
Classifier: Intended Audience :: Developers
Classifier: License :: OSI Approved :: MIT License
Classifier: Operating System :: OS Independent
Classifier: Programming Language :: Python
Classifier: Topic :: Internet :: WWW/HTTP :: Dynamic Content
Classifier: Topic :: Software Development :: Libraries :: Python Modules
